{
  "db_name": "PostgreSQL",
  "query": "\n        INSERT INTO project_extensions (project_id, extension, extension_type, spec)\n        VALUES ($1, $2, $3, $4)\n        RETURNING project_id, extension, extension_type,\n                  spec as \"spec: Value\",\n                  status as \"status: Value\",\n                  created_at, updated_at, deleted_at\n        ",
  "describe": {
    "columns": [
      {
        "ordinal": 0,
        "name": "project_id",
        "type_info": "Uuid"
      },
      {
        "ordinal": 1,
        "name": "extension",
        "type_info": "Varchar"
      },
      {
        "ordinal": 2,
        "name": "extension_type",
        "type_info": "Varchar"
      },
      {
        "ordinal": 3,
        "name": "spec: Value",
        "type_info": "Jsonb"
      },
      {
        "ordinal": 4,
        "name": "status: Value",
        "type_info": "Jsonb"
      },
      {
        "ordinal": 5,
        "name": "created_at",
        "type_info": "Timestamptz"
      },
      {
        "ordinal": 6,
        "name": "updated_at",
        "type_info": "Timestamptz"
      },
      {
        "ordinal": 7,
        "name": "deleted_at",
        "type_info": "Timestamptz"
      }
    ],
    "parameters": {
      "Left": [
        "Uuid",
        "Varchar",
        "Varchar",
        "Jsonb"
      ]
    },
    "nullable": [
      false,
      false,
      false,
      false,
      true,
      false,
      false,
      true
    ]
  },
  "hash": "47b0ff45bbcd65b42f4137d13cd5a91364103470a894d5e445cc1c2d40090559"
}
