{
  "db_name": "PostgreSQL",
  "query": "\n        SELECT id, project_id, domain, is_primary, created_at, updated_at\n        FROM project_custom_domains\n        WHERE project_id = ANY($1)\n        ORDER BY project_id, domain ASC\n        ",
  "describe": {
    "columns": [
      {
        "ordinal": 0,
        "name": "id",
        "type_info": "Uuid"
      },
      {
        "ordinal": 1,
        "name": "project_id",
        "type_info": "Uuid"
      },
      {
        "ordinal": 2,
        "name": "domain",
        "type_info": "Text"
      },
      {
        "ordinal": 3,
        "name": "is_primary",
        "type_info": "Bool"
      },
      {
        "ordinal": 4,
        "name": "created_at",
        "type_info": "Timestamptz"
      },
      {
        "ordinal": 5,
        "name": "updated_at",
        "type_info": "Timestamptz"
      }
    ],
    "parameters": {
      "Left": [
        "UuidArray"
      ]
    },
    "nullable": [
      false,
      false,
      false,
      false,
      false,
      false
    ]
  },
  "hash": "49143bfb63192415937a42ad68716271bf98619f244b1135d26add8d11b9b988"
}
