{
  "db_name": "PostgreSQL",
  "query": "\n        SELECT id, project_id, user_id, issuer_url, claims, sequence,\n               deleted_at, created_at, updated_at\n        FROM service_accounts\n        WHERE issuer_url = $1 AND deleted_at IS NULL\n        ",
  "describe": {
    "columns": [
      {
        "ordinal": 0,
        "name": "id",
        "type_info": "Uuid"
      },
      {
        "ordinal": 1,
        "name": "project_id",
        "type_info": "Uuid"
      },
      {
        "ordinal": 2,
        "name": "user_id",
        "type_info": "Uuid"
      },
      {
        "ordinal": 3,
        "name": "issuer_url",
        "type_info": "Text"
      },
      {
        "ordinal": 4,
        "name": "claims",
        "type_info": "Jsonb"
      },
      {
        "ordinal": 5,
        "name": "sequence",
        "type_info": "Int4"
      },
      {
        "ordinal": 6,
        "name": "deleted_at",
        "type_info": "Timestamptz"
      },
      {
        "ordinal": 7,
        "name": "created_at",
        "type_info": "Timestamptz"
      },
      {
        "ordinal": 8,
        "name": "updated_at",
        "type_info": "Timestamptz"
      }
    ],
    "parameters": {
      "Left": [
        "Text"
      ]
    },
    "nullable": [
      false,
      false,
      false,
      false,
      false,
      false,
      true,
      false,
      false
    ]
  },
  "hash": "4d816dc567e76ce9b861bde4582819c655fa4078211c2997acc8004eb76a6a62"
}
